scoringrules/__init__.py
scoringrules/_brier.py
scoringrules/_crps.py
scoringrules/_energy.py
scoringrules/_error_spread.py
scoringrules/_interval.py
scoringrules/_kernels.py
scoringrules/_logs.py
scoringrules/_quantile.py
scoringrules/_variogram.py
scoringrules/backend/__init__.py
scoringrules/backend/base.py
scoringrules/backend/jax.py
scoringrules/backend/numpy.py
scoringrules/backend/registry.py
scoringrules/backend/tensorflow.py
scoringrules/backend/torch.py
scoringrules/core/__init__.py
scoringrules/core/brier.py
scoringrules/core/logarithmic.py
scoringrules/core/stats.py
scoringrules/core/typing.py
scoringrules/core/utils.py
scoringrules/core/crps/__init__.py
scoringrules/core/crps/_approx.py
scoringrules/core/crps/_closed.py
scoringrules/core/crps/_gufuncs.py
scoringrules/core/energy/__init__.py
scoringrules/core/energy/_gufuncs.py
scoringrules/core/energy/_score.py
scoringrules/core/error_spread/__init__.py
scoringrules/core/error_spread/_gufunc.py
scoringrules/core/error_spread/_score.py
scoringrules/core/interval/__init__.py
scoringrules/core/interval/_gufunc.py
scoringrules/core/interval/_score.py
scoringrules/core/kernels/__init__.py
scoringrules/core/kernels/_approx.py
scoringrules/core/kernels/_gufuncs.py
scoringrules/core/variogram/__init__.py
scoringrules/core/variogram/_gufuncs.py
scoringrules/core/variogram/_score.py
scoringrules/visualization/__init__.py
scoringrules/visualization/reliability.py
scoringrules-0.8.0.dist-info/METADATA
scoringrules-0.8.0.dist-info/WHEEL
scoringrules-0.8.0.dist-info/licenses/LICENSE
scoringrules-0.8.0.dist-info/RECORD
