Metadata-Version: 2.4
Name: scoringrules
Version: 0.8.0
Summary: Scoring rules for probabilistic forecast evaluation.
Project-URL: Homepage, https://github.com/frazane/scoringrules
Project-URL: Documentation, https://frazane.github.io/scoringrules
Project-URL: Issues, https://github.com/frazane/scoringrules/issues
Author-email: Francesco Zanetta <zanetta.francesco@gmail.com>, Sam Allen <sam.allen@stat.math.ethz.ch>
License: 
License-File: LICENSE
Keywords: forecasting,probabilistic,verification
Classifier: Development Status :: 4 - Beta
Classifier: Intended Audience :: Developers
Classifier: Intended Audience :: Science/Research
Classifier: License :: OSI Approved :: Apache Software License
Classifier: License :: OSI Approved :: MIT License
Classifier: Programming Language :: Python :: 3.10
Classifier: Programming Language :: Python :: 3.11
Classifier: Programming Language :: Python :: 3.12
Classifier: Topic :: Scientific/Engineering :: Mathematics
Requires-Python: >=3.10
Requires-Dist: numpy>=1.25.0
Requires-Dist: scipy>=1.10.0
Provides-Extra: jax
Requires-Dist: jax>=0.4.31; extra == 'jax'
Provides-Extra: numba
Requires-Dist: numba>=0.60.0; extra == 'numba'
Provides-Extra: tensorflow
Requires-Dist: tensorflow>=2.17.0; extra == 'tensorflow'
Provides-Extra: torch
Requires-Dist: torch>=2.4.1; extra == 'torch'
